{
  "swimmer": "Micaela Silva Garzon",
  "data": [
    {
      "event": "200 FR",
      "times": [
        {
          "location": "12/5/2024, West Windsor-Plainsboro North (101) at Hightstown (69)",
          "time": "3:30.19"
        },
        {
          "location": "12/13/2024, Princeton (96) at Hightstown (69)",
          "time": "2:58.64"
        },
        {
          "location": "12/17/2024, Hightstown (125) at Trenton (37)",
          "time": "2:48.92"
        },
        {
          "location": "12/19/2024, Hightstown (57) at Hopewell Valley (112)",
          "time": "2:43.23"
        }
      ]
    },
    {
      "event": "400 FR",
      "times": [
        {
          "location": "12/13/2024, Princeton (96) at Hightstown (69)",
          "time": "6:39.97"
        },
        {
          "location": "12/17/2024, Hightstown (125) at Trenton (37)",
          "time": "6:32.24"
        },
        {
          "location": "1/7/2025, Lawrence (99) at Hightstown (71)",
          "time": "5:40.72"
        },
        {
          "location": "1/16/2025, Hightstown (118) at Hamilton West (52)",
          "time": "5:44.15"
        }
      ]
    },
    {
      "event": "500 Free",
      "times": [
        {
          "location": "12/13/2024, Princeton (96) at Hightstown (69)",
          "time": "09:16.77"
        }
      ]
    }
  ]
}